optix/__init__.py
optix/py.typed
jax_optix-0.1.10.dist-info/METADATA
jax_optix-0.1.10.dist-info/WHEEL
jax_optix-0.1.10.dist-info/licenses/LICENSE.md
jax_optix-0.1.10.dist-info/RECORD
