Metadata-Version: 2.4
Name: jax-optix
Version: 0.1.10
Summary: Zero-overhead functional lensing for JAX PyTrees
Project-URL: Homepage, https://github.com/jonkhler/optix
Author-email: Jonas Köhler <jonas.koehler.ks@gmail.com>
License: MIT
License-File: LICENSE.md
Keywords: equinox,functional,jax,lens,optics
Requires-Python: >=3.12
Requires-Dist: equinox>=0.11.11
Requires-Dist: jax>=0.5.0
Requires-Dist: pytest>=8.3.4
